genomenotebook/__init__.py
genomenotebook/_modidx.py
genomenotebook/browser.py
genomenotebook/glyphs.py
genomenotebook/plot.py
genomenotebook/track.py
genomenotebook/utils.py
genomenotebook/data/ChIP-ACCCA-1.bw
genomenotebook/data/ChIP-ACCCA-2.bw
genomenotebook/data/GCA_000189435.3_ASM18943v3_genomic.fna
genomenotebook/data/GCA_000189435.3_ASM18943v3_genomic.gff
genomenotebook/data/MG1655_U00096.fasta
genomenotebook/data/MG1655_U00096.gff3
genomenotebook/data/MT_nbs.gb
genomenotebook/data/U00096.gb
genomenotebook/data/__init__.py
genomenotebook/data/colored_genbank.fasta
genomenotebook/data/colored_genbank.gb
genomenotebook/data/colored_genbank.gff
genomenotebook/data/hmf_pathway_variants.gbk
genomenotebook/data/jmh43.fna
genomenotebook/data/jmh43.gff
genomenotebook/data/jmh43_coverage.bw
genomenotebook/javascript/__init__.py
genomenotebook/javascript/glyph_update_callback_code.js
genomenotebook/javascript/js_callback_code.py
genomenotebook/javascript/next_button_code.js
genomenotebook/javascript/previous_button_code.js
genomenotebook/javascript/search_callback_code.js
genomenotebook/javascript/sequence_search_code.js
genomenotebook/javascript/track_callback_code.js
genomenotebook/javascript/x_range_change_callback_code.js
genomenotebook-1.0.0.dist-info/LICENSE
genomenotebook-1.0.0.dist-info/METADATA
genomenotebook-1.0.0.dist-info/WHEEL
genomenotebook-1.0.0.dist-info/entry_points.txt
genomenotebook-1.0.0.dist-info/top_level.txt
genomenotebook-1.0.0.dist-info/RECORD
