Metadata-Version: 2.1
Name: genomenotebook
Version: 1.0.0
Summary: A genome browser in your Jupyter notebook
Home-page: https://github.com/dbikard/genomenotebook
Author: David Bikard
Author-email: dbikard@pasteur.fr
License: Apache Software License 2.0
Keywords: nbdev jupyter notebook python
Classifier: Development Status :: 4 - Beta
Classifier: Intended Audience :: Developers
Classifier: Natural Language :: English
Classifier: Programming Language :: Python :: 3.7
Classifier: Programming Language :: Python :: 3.8
Classifier: Programming Language :: Python :: 3.9
Classifier: Programming Language :: Python :: 3.10
Classifier: License :: OSI Approved :: Apache Software License
Requires-Python: >=3.7
License-File: LICENSE
Requires-Dist: numpy>=1.23.5
Requires-Dist: biopython>=1.78
Requires-Dist: pandas>=1.5.3
Requires-Dist: bokeh<3.3.0,>=3.1.0
Requires-Dist: fastcore
Requires-Dist: jupyter
Requires-Dist: selenium
Requires-Dist: svgutils
Requires-Dist: chromedriver_binary
Provides-Extra: dev
Requires-Dist: pyBigWig; extra == "dev"
